came_pytorch/CAME.py
came_pytorch/__init__.py
came_pytorch-0.1.3.dist-info/LICENSE
came_pytorch-0.1.3.dist-info/METADATA
came_pytorch-0.1.3.dist-info/WHEEL
came_pytorch-0.1.3.dist-info/top_level.txt
came_pytorch-0.1.3.dist-info/RECORD
