Metadata-Version: 2.1
Name: came-pytorch
Version: 0.1.3
Summary: CAME Optimizer - Pytorch Version
Home-page: https://github.com/yangluo7/CAME/
Author: Yang Luo
Author-email: yangluo@comp.nus.edu.sg
License: MIT
Keywords: artificial intelligence,deep learning,optimizers,memory efficient
Classifier: Programming Language :: Python :: 3.6
Classifier: License :: OSI Approved :: MIT License
Classifier: Intended Audience :: Developers
Classifier: Topic :: Scientific/Engineering :: Artificial Intelligence
Requires-Python: >=3.6
License-File: LICENSE
Requires-Dist: torch >=1.6
